jtow/__init__.py
jtow/auto_jtow.py
jtow/examine_cubes.py
jtow/jtow.py
jtow/make_WL_cube.py
jtow/make_minisegments.py
jtow/make_pairwise_cds.py
jtow/make_ratio_images.py
jtow/quick_ff_divide.py
jtow/temporal_clean.py
jtow/wrap_all.py
jtow/params/default_params.yaml
jtow-0.1.5.data/scripts/roeba_run
jtow-0.1.5.dist-info/AUTHORS.rst
jtow-0.1.5.dist-info/LICENSE
jtow-0.1.5.dist-info/METADATA
jtow-0.1.5.dist-info/WHEEL
jtow-0.1.5.dist-info/top_level.txt
jtow-0.1.5.dist-info/RECORD
