Metadata-Version: 2.1
Name: jtow
Version: 0.1.5
Summary: JWST Time series Observation Wrapper.
Home-page: https://github.com/eas342/jtow
Author: Everett Schlawin
Author-email: granfalloontoyballoon@hotmail.com
License: MIT license
Keywords: jtow
Classifier: Development Status :: 2 - Pre-Alpha
Classifier: Intended Audience :: Developers
Classifier: License :: OSI Approved :: MIT License
Classifier: Natural Language :: English
Classifier: Programming Language :: Python :: 3
Classifier: Programming Language :: Python :: 3.6
Classifier: Programming Language :: Python :: 3.7
Classifier: Programming Language :: Python :: 3.8
Requires-Python: >=3.6
License-File: LICENSE
License-File: AUTHORS.rst
Requires-Dist: tshirt >=0.3.1
Requires-Dist: jwst
Requires-Dist: splintegrate
Requires-Dist: scikit-learn
